kanban_tui/__init__.py
kanban_tui/app.py
kanban_tui/config.py
kanban_tui/constants.py
kanban_tui/py.typed
kanban_tui/skills.py
kanban_tui/utils.py
kanban_tui/assets/SKILL.md
kanban_tui/assets/style.tcss
kanban_tui/backends/__init__.py
kanban_tui/backends/auth.py
kanban_tui/backends/base.py
kanban_tui/backends/claude/__init__.py
kanban_tui/backends/claude/backend.py
kanban_tui/backends/jira/__init__.py
kanban_tui/backends/jira/backend.py
kanban_tui/backends/jira/jira_api.py
kanban_tui/backends/jira/models.py
kanban_tui/backends/sqlite/__init__.py
kanban_tui/backends/sqlite/backend.py
kanban_tui/backends/sqlite/database.py
kanban_tui/backends/sqlite/migrations/__init__.py
kanban_tui/backends/sqlite/migrations/migration_v0_13_0.sql
kanban_tui/backends/sqlite/migrations/migration_v0_14_0.sql
kanban_tui/classes/__init__.py
kanban_tui/classes/board.py
kanban_tui/classes/category.py
kanban_tui/classes/column.py
kanban_tui/classes/logevent.py
kanban_tui/classes/py.typed
kanban_tui/classes/task.py
kanban_tui/cli/__init__.py
kanban_tui/cli/board_commands.py
kanban_tui/cli/category_commands.py
kanban_tui/cli/column_commands.py
kanban_tui/cli/demo_commands.py
kanban_tui/cli/general_commands.py
kanban_tui/cli/mcp_commands.py
kanban_tui/cli/skills_commands.py
kanban_tui/cli/task_commands.py
kanban_tui/modal/__init__.py
kanban_tui/modal/modal_auth_screen.py
kanban_tui/modal/modal_board_screen.py
kanban_tui/modal/modal_category_screen.py
kanban_tui/modal/modal_confirm_screen.py
kanban_tui/modal/modal_jira_board_screen.py
kanban_tui/modal/modal_jira_url_screen.py
kanban_tui/modal/modal_settings.py
kanban_tui/modal/modal_task_screen.py
kanban_tui/screens/board_screen.py
kanban_tui/screens/overview_screen.py
kanban_tui/screens/settings_screen.py
kanban_tui/textual_datepicker/__init__.py
kanban_tui/textual_datepicker/_date_picker.py
kanban_tui/textual_datepicker/_date_select.py
kanban_tui/textual_datepicker/py.typed
kanban_tui/widgets/__init__.py
kanban_tui/widgets/board_widgets.py
kanban_tui-0.17.1.dist-info/METADATA
kanban_tui-0.17.1.dist-info/WHEEL
kanban_tui-0.17.1.dist-info/entry_points.txt
kanban_tui-0.17.1.dist-info/licenses/LICENSE.txt
kanban_tui-0.17.1.dist-info/RECORD
