Metadata-Version: 2.4
Name: kanban-tui
Version: 0.17.1
Summary: customizable task tui powered by textual usable by agents
Project-URL: Repository, https://github.com/Zaloog/kanban-tui
Project-URL: Changelog, https://github.com/Zaloog/kanban-tui/blob/main/CHANGELOG.md
Author-email: Zaloog <gramslars@gmail.com>
License: MIT
License-File: LICENSE.txt
Keywords: cli,kanban,mcp,python,tasks,textual,tui
Classifier: Development Status :: 3 - Alpha
Classifier: License :: OSI Approved :: MIT License
Classifier: Operating System :: OS Independent
Classifier: Programming Language :: Python
Classifier: Programming Language :: Python :: 3 :: Only
Classifier: Programming Language :: Python :: 3.11
Classifier: Programming Language :: Python :: 3.12
Classifier: Programming Language :: Python :: 3.13
Classifier: Programming Language :: Python :: 3.14
Requires-Python: >=3.11
Requires-Dist: click>=8.1.7
Requires-Dist: pydantic-settings>=2.10.1
Requires-Dist: pydantic>=2.11.7
Requires-Dist: python-dateutil>=2.9.0.post0
Requires-Dist: textual-jumper>=0.2.0
Requires-Dist: textual-plotext>=1.0.0
Requires-Dist: textual>=6.1.0
Requires-Dist: tomli-w>=1.2.0
Requires-Dist: tzdata>=2025.2
Requires-Dist: xdg-base-dirs>=6.0.2
Provides-Extra: jira
Requires-Dist: atlassian-python-api>=4.0.7; extra == 'jira'
Provides-Extra: mcp
Requires-Dist: pycli-mcp>=0.3.0; extra == 'mcp'
Provides-Extra: web
Requires-Dist: textual-serve>=1.1.1; extra == 'web'
